{
  "last_updated": "2026-02-16",
  "season": "2024",
  "methodology": "skill_delta = playoff_skill - regular_season_skill (using RS model for both)",
  "min_rs_pitches": 250,
  "min_po_pitches": 50,
  "pitchers": [
    {
      "pitcher_id": 623352,
      "name": "Josh Hader",
      "team": "HOU",
      "rs_pitches": 1148,
      "rs_skill": 0.0489,
      "po_pitches": 50,
      "po_skill": -0.1343,
      "skill_delta": -0.1832,
      "category": "big_faller",
      "confidence": "low",
      "rank": 1
    },
    {
      "pitcher_id": 681911,
      "name": "Alex Vesia",
      "team": "LAD",
      "rs_pitches": 1107,
      "rs_skill": -0.0296,
      "po_pitches": 92,
      "po_skill": 0.1308,
      "skill_delta": 0.1604,
      "category": "big_riser",
      "confidence": "low",
      "rank": 2
    },
    {
      "pitcher_id": 664776,
      "name": "Jake Cousins",
      "team": "NYY",
      "rs_pitches": 638,
      "rs_skill": -0.0398,
      "po_pitches": 115,
      "po_skill": 0.1064,
      "skill_delta": 0.1462,
      "category": "big_riser",
      "confidence": "medium",
      "rank": 3
    },
    {
      "pitcher_id": 663460,
      "name": "Kris Bubic",
      "team": "KC",
      "rs_pitches": 467,
      "rs_skill": 0.047,
      "po_pitches": 77,
      "po_skill": -0.0988,
      "skill_delta": -0.1458,
      "category": "big_faller",
      "confidence": "low",
      "rank": 4
    },
    {
      "pitcher_id": 621111,
      "name": "Walker Buehler",
      "team": "LAD",
      "rs_pitches": 1330,
      "rs_skill": -0.0273,
      "po_pitches": 258,
      "po_skill": 0.099,
      "skill_delta": 0.1263,
      "category": "big_riser",
      "confidence": "high",
      "rank": 5
    },
    {
      "pitcher_id": 554430,
      "name": "Zack Wheeler",
      "team": "PHI",
      "rs_pitches": 3126,
      "rs_skill": -0.0035,
      "po_pitches": 110,
      "po_skill": 0.1148,
      "skill_delta": 0.1183,
      "category": "big_riser",
      "confidence": "medium",
      "rank": 6
    },
    {
      "pitcher_id": 571510,
      "name": "Matthew Boyd",
      "team": "CLE",
      "rs_pitches": 667,
      "rs_skill": 0.0527,
      "po_pitches": 179,
      "po_skill": 0.1673,
      "skill_delta": 0.1146,
      "category": "big_riser",
      "confidence": "medium",
      "rank": 7
    },
    {
      "pitcher_id": 621107,
      "name": "Zach Eflin",
      "team": "BAL",
      "rs_pitches": 2364,
      "rs_skill": -0.026,
      "po_pitches": 74,
      "po_skill": -0.1296,
      "skill_delta": -0.1036,
      "category": "big_faller",
      "confidence": "low",
      "rank": 8
    },
    {
      "pitcher_id": 658648,
      "name": "Pedro Avila",
      "team": "CLE",
      "rs_pitches": 1408,
      "rs_skill": 0.0058,
      "po_pitches": 52,
      "po_skill": 0.1007,
      "skill_delta": 0.0949,
      "category": "big_riser",
      "confidence": "low",
      "rank": 9
    },
    {
      "pitcher_id": 623465,
      "name": "Evan Phillips",
      "team": "LAD",
      "rs_pitches": 913,
      "rs_skill": -0.0266,
      "po_pitches": 101,
      "po_skill": -0.1206,
      "skill_delta": -0.094,
      "category": "big_faller",
      "confidence": "medium",
      "rank": 10
    },
    {
      "pitcher_id": 605400,
      "name": "Aaron Nola",
      "team": "PHI",
      "rs_pitches": 3186,
      "rs_skill": -0.0057,
      "po_pitches": 86,
      "po_skill": 0.0882,
      "skill_delta": 0.0939,
      "category": "big_riser",
      "confidence": "low",
      "rank": 11
    },
    {
      "pitcher_id": 607455,
      "name": "Anthony Banda",
      "team": "LAD",
      "rs_pitches": 772,
      "rs_skill": 0.0032,
      "po_pitches": 147,
      "po_skill": -0.0882,
      "skill_delta": -0.0914,
      "category": "big_faller",
      "confidence": "medium",
      "rank": 12
    },
    {
      "pitcher_id": 657585,
      "name": "Reed Garrett",
      "team": "NYM",
      "rs_pitches": 952,
      "rs_skill": 0.0529,
      "po_pitches": 126,
      "po_skill": -0.0345,
      "skill_delta": -0.0874,
      "category": "big_faller",
      "confidence": "medium",
      "rank": 13
    },
    {
      "pitcher_id": 543037,
      "name": "Gerrit Cole",
      "team": "NYY",
      "rs_pitches": 1527,
      "rs_skill": -0.0215,
      "po_pitches": 452,
      "po_skill": -0.1066,
      "skill_delta": -0.0851,
      "category": "big_faller",
      "confidence": "high",
      "rank": 14
    },
    {
      "pitcher_id": 592454,
      "name": "Tommy Kahnle",
      "team": "NYY",
      "rs_pitches": 732,
      "rs_skill": 0.0621,
      "po_pitches": 143,
      "po_skill": -0.0218,
      "skill_delta": -0.0839,
      "category": "big_faller",
      "confidence": "medium",
      "rank": 15
    },
    {
      "pitcher_id": 506433,
      "name": "Yu Darvish",
      "team": "SD",
      "rs_pitches": 1249,
      "rs_skill": 0.0111,
      "po_pitches": 159,
      "po_skill": -0.0708,
      "skill_delta": -0.0819,
      "category": "big_faller",
      "confidence": "medium",
      "rank": 16
    },
    {
      "pitcher_id": 670167,
      "name": "John Schreiber",
      "team": "KC",
      "rs_pitches": 891,
      "rs_skill": -0.0083,
      "po_pitches": 74,
      "po_skill": 0.0735,
      "skill_delta": 0.0818,
      "category": "big_riser",
      "confidence": "low",
      "rank": 17
    },
    {
      "pitcher_id": 650911,
      "name": "Cristopher S\u00e1nchez",
      "team": "PHI",
      "rs_pitches": 2795,
      "rs_skill": -0.0387,
      "po_pitches": 88,
      "po_skill": 0.0404,
      "skill_delta": 0.0791,
      "category": "big_riser",
      "confidence": "low",
      "rank": 18
    },
    {
      "pitcher_id": 671922,
      "name": "Cade Smith",
      "team": "CLE",
      "rs_pitches": 1158,
      "rs_skill": 0.0063,
      "po_pitches": 152,
      "po_skill": 0.0844,
      "skill_delta": 0.0781,
      "category": "big_riser",
      "confidence": "medium",
      "rank": 19
    },
    {
      "pitcher_id": 656629,
      "name": "Michael Kopech",
      "team": "LAD",
      "rs_pitches": 1138,
      "rs_skill": -0.0428,
      "po_pitches": 173,
      "po_skill": -0.119,
      "skill_delta": -0.0762,
      "category": "big_faller",
      "confidence": "medium",
      "rank": 20
    },
    {
      "pitcher_id": 593423,
      "name": "Frankie Montas",
      "team": "MIL",
      "rs_pitches": 2627,
      "rs_skill": 0.0081,
      "po_pitches": 60,
      "po_skill": -0.066,
      "skill_delta": -0.0741,
      "category": "big_faller",
      "confidence": "low",
      "rank": 21
    },
    {
      "pitcher_id": 676428,
      "name": "Brant Hurter",
      "team": "DET",
      "rs_pitches": 645,
      "rs_skill": 0.0036,
      "po_pitches": 84,
      "po_skill": -0.0688,
      "skill_delta": -0.0724,
      "category": "big_faller",
      "confidence": "low",
      "rank": 22
    },
    {
      "pitcher_id": 661563,
      "name": "Luis Gil",
      "team": "NYY",
      "rs_pitches": 2624,
      "rs_skill": -0.0173,
      "po_pitches": 146,
      "po_skill": -0.0881,
      "skill_delta": -0.0708,
      "category": "big_faller",
      "confidence": "medium",
      "rank": 23
    },
    {
      "pitcher_id": 689147,
      "name": "Orion Kerkering",
      "team": "PHI",
      "rs_pitches": 1055,
      "rs_skill": 0.0011,
      "po_pitches": 63,
      "po_skill": 0.0716,
      "skill_delta": 0.0705,
      "category": "big_riser",
      "confidence": "low",
      "rank": 24
    },
    {
      "pitcher_id": 669093,
      "name": "Jeremiah Estrada",
      "team": "SD",
      "rs_pitches": 998,
      "rs_skill": 0.0193,
      "po_pitches": 82,
      "po_skill": -0.0485,
      "skill_delta": -0.0678,
      "category": "big_faller",
      "confidence": "low",
      "rank": 25
    },
    {
      "pitcher_id": 683769,
      "name": "Hunter Gaddis",
      "team": "CLE",
      "rs_pitches": 1071,
      "rs_skill": -0.0491,
      "po_pitches": 154,
      "po_skill": 0.0182,
      "skill_delta": 0.0673,
      "category": "big_riser",
      "confidence": "medium",
      "rank": 26
    },
    {
      "pitcher_id": 669212,
      "name": "Eli Morgan",
      "team": "CLE",
      "rs_pitches": 645,
      "rs_skill": -0.0378,
      "po_pitches": 69,
      "po_skill": 0.0242,
      "skill_delta": 0.062,
      "category": "big_riser",
      "confidence": "low",
      "rank": 27
    },
    {
      "pitcher_id": 622663,
      "name": "Luis Severino",
      "team": "NYM",
      "rs_pitches": 2877,
      "rs_skill": -0.0172,
      "po_pitches": 290,
      "po_skill": -0.0778,
      "skill_delta": -0.0606,
      "category": "big_faller",
      "confidence": "high",
      "rank": 28
    },
    {
      "pitcher_id": 669203,
      "name": "Corbin Burnes",
      "team": "BAL",
      "rs_pitches": 2991,
      "rs_skill": -0.0008,
      "po_pitches": 84,
      "po_skill": -0.06,
      "skill_delta": -0.0592,
      "category": "big_faller",
      "confidence": "low",
      "rank": 29
    },
    {
      "pitcher_id": 689017,
      "name": "Landon Knack",
      "team": "LAD",
      "rs_pitches": 1146,
      "rs_skill": -0.0108,
      "po_pitches": 131,
      "po_skill": -0.0688,
      "skill_delta": -0.058,
      "category": "big_faller",
      "confidence": "medium",
      "rank": 30
    },
    {
      "pitcher_id": 672582,
      "name": "Angel Zerpa",
      "team": "KC",
      "rs_pitches": 948,
      "rs_skill": -0.0297,
      "po_pitches": 79,
      "po_skill": 0.026,
      "skill_delta": 0.0557,
      "category": "big_riser",
      "confidence": "low",
      "rank": 31
    },
    {
      "pitcher_id": 656731,
      "name": "Tylor Megill",
      "team": "NYM",
      "rs_pitches": 1358,
      "rs_skill": 0.0324,
      "po_pitches": 105,
      "po_skill": -0.0225,
      "skill_delta": -0.0549,
      "category": "big_faller",
      "confidence": "medium",
      "rank": 32
    },
    {
      "pitcher_id": 686613,
      "name": "Hunter Brown",
      "team": "HOU",
      "rs_pitches": 2782,
      "rs_skill": 0.0168,
      "po_pitches": 99,
      "po_skill": -0.0351,
      "skill_delta": -0.0519,
      "category": "big_faller",
      "confidence": "low",
      "rank": 33
    },
    {
      "pitcher_id": 656849,
      "name": "David Peterson",
      "team": "NYM",
      "rs_pitches": 1862,
      "rs_skill": -0.0005,
      "po_pitches": 200,
      "po_skill": 0.0511,
      "skill_delta": 0.0516,
      "category": "big_riser",
      "confidence": "high",
      "rank": 34
    },
    {
      "pitcher_id": 689225,
      "name": "Beau Brieske",
      "team": "DET",
      "rs_pitches": 1150,
      "rs_skill": -0.0154,
      "po_pitches": 87,
      "po_skill": 0.0321,
      "skill_delta": 0.0475,
      "category": "riser",
      "confidence": "low",
      "rank": 35
    },
    {
      "pitcher_id": 605280,
      "name": "Clay Holmes",
      "team": "NYY",
      "rs_pitches": 1081,
      "rs_skill": 0.0489,
      "po_pitches": 172,
      "po_skill": 0.0016,
      "skill_delta": -0.0473,
      "category": "faller",
      "confidence": "medium",
      "rank": 36
    },
    {
      "pitcher_id": 666142,
      "name": "Cole Ragans",
      "team": "KC",
      "rs_pitches": 3112,
      "rs_skill": 0.0058,
      "po_pitches": 167,
      "po_skill": -0.0415,
      "skill_delta": -0.0473,
      "category": "faller",
      "confidence": "medium",
      "rank": 37
    },
    {
      "pitcher_id": 596133,
      "name": "Luke Weaver",
      "team": "NYY",
      "rs_pitches": 1369,
      "rs_skill": 0.0343,
      "po_pitches": 213,
      "po_skill": -0.0126,
      "skill_delta": -0.0469,
      "category": "faller",
      "confidence": "high",
      "rank": 38
    },
    {
      "pitcher_id": 624133,
      "name": "Ranger Su\u00e1rez",
      "team": "PHI",
      "rs_pitches": 2261,
      "rs_skill": -0.0067,
      "po_pitches": 97,
      "po_skill": -0.0521,
      "skill_delta": -0.0454,
      "category": "faller",
      "confidence": "low",
      "rank": 39
    },
    {
      "pitcher_id": 661403,
      "name": "Emmanuel Clase",
      "team": "CLE",
      "rs_pitches": 981,
      "rs_skill": 0.0102,
      "po_pitches": 123,
      "po_skill": 0.053,
      "skill_delta": 0.0428,
      "category": "riser",
      "confidence": "medium",
      "rank": 40
    },
    {
      "pitcher_id": 656427,
      "name": "Jack Flaherty",
      "team": "LAD",
      "rs_pitches": 2468,
      "rs_skill": -0.0102,
      "po_pitches": 387,
      "po_skill": -0.0526,
      "skill_delta": -0.0424,
      "category": "faller",
      "confidence": "high",
      "rank": 41
    },
    {
      "pitcher_id": 668674,
      "name": "Lucas Erceg",
      "team": "KC",
      "rs_pitches": 941,
      "rs_skill": 0.0545,
      "po_pitches": 98,
      "po_skill": 0.0935,
      "skill_delta": 0.039,
      "category": "riser",
      "confidence": "low",
      "rank": 42
    },
    {
      "pitcher_id": 518489,
      "name": "Ryan Brasier",
      "team": "LAD",
      "rs_pitches": 374,
      "rs_skill": -0.0453,
      "po_pitches": 138,
      "po_skill": -0.0073,
      "skill_delta": 0.038,
      "category": "riser",
      "confidence": "medium",
      "rank": 43
    },
    {
      "pitcher_id": 656945,
      "name": "Tanner Scott",
      "team": "SD",
      "rs_pitches": 1150,
      "rs_skill": -0.0084,
      "po_pitches": 62,
      "po_skill": -0.0459,
      "skill_delta": -0.0375,
      "category": "faller",
      "confidence": "low",
      "rank": 44
    },
    {
      "pitcher_id": 642547,
      "name": "Freddy Peralta",
      "team": "MIL",
      "rs_pitches": 3031,
      "rs_skill": -0.0007,
      "po_pitches": 81,
      "po_skill": -0.038,
      "skill_delta": -0.0373,
      "category": "faller",
      "confidence": "low",
      "rank": 45
    },
    {
      "pitcher_id": 808967,
      "name": "Yoshinobu Yamamoto",
      "team": "LAD",
      "rs_pitches": 1459,
      "rs_skill": -0.0029,
      "po_pitches": 281,
      "po_skill": -0.0375,
      "skill_delta": -0.0346,
      "category": "faller",
      "confidence": "high",
      "rank": 46
    },
    {
      "pitcher_id": 641835,
      "name": "Tim Mayza",
      "team": "NYY",
      "rs_pitches": 714,
      "rs_skill": -0.0108,
      "po_pitches": 52,
      "po_skill": -0.0452,
      "skill_delta": -0.0344,
      "category": "faller",
      "confidence": "low",
      "rank": 47
    },
    {
      "pitcher_id": 543339,
      "name": "Daniel Hudson",
      "team": "LAD",
      "rs_pitches": 997,
      "rs_skill": -0.0031,
      "po_pitches": 93,
      "po_skill": -0.0368,
      "skill_delta": -0.0337,
      "category": "faller",
      "confidence": "low",
      "rank": 48
    },
    {
      "pitcher_id": 664208,
      "name": "Phil Maton",
      "team": "NYM",
      "rs_pitches": 1054,
      "rs_skill": -0.0128,
      "po_pitches": 133,
      "po_skill": 0.0202,
      "skill_delta": 0.033,
      "category": "riser",
      "confidence": "medium",
      "rank": 49
    },
    {
      "pitcher_id": 676684,
      "name": "Will Vest",
      "team": "DET",
      "rs_pitches": 1149,
      "rs_skill": -0.0364,
      "po_pitches": 86,
      "po_skill": -0.0061,
      "skill_delta": 0.0303,
      "category": "riser",
      "confidence": "low",
      "rank": 50
    },
    {
      "pitcher_id": 669674,
      "name": "Sam Long",
      "team": "KC",
      "rs_pitches": 700,
      "rs_skill": -0.0032,
      "po_pitches": 69,
      "po_skill": -0.0334,
      "skill_delta": -0.0302,
      "category": "faller",
      "confidence": "low",
      "rank": 51
    },
    {
      "pitcher_id": 595014,
      "name": "Blake Treinen",
      "team": "LAD",
      "rs_pitches": 735,
      "rs_skill": -0.0026,
      "po_pitches": 224,
      "po_skill": -0.0312,
      "skill_delta": -0.0286,
      "category": "faller",
      "confidence": "high",
      "rank": 52
    },
    {
      "pitcher_id": 657376,
      "name": "Clarke Schmidt",
      "team": "NYY",
      "rs_pitches": 1445,
      "rs_skill": 0.0468,
      "po_pitches": 216,
      "po_skill": 0.0208,
      "skill_delta": -0.026,
      "category": "faller",
      "confidence": "high",
      "rank": 53
    },
    {
      "pitcher_id": 650633,
      "name": "Michael King",
      "team": "SD",
      "rs_pitches": 2858,
      "rs_skill": 0.0217,
      "po_pitches": 166,
      "po_skill": -0.0039,
      "skill_delta": -0.0256,
      "category": "faller",
      "confidence": "medium",
      "rank": 54
    },
    {
      "pitcher_id": 676130,
      "name": "Jos\u00e9 Butt\u00f3",
      "team": "NYM",
      "rs_pitches": 1216,
      "rs_skill": 0.0267,
      "po_pitches": 133,
      "po_skill": 0.0517,
      "skill_delta": 0.025,
      "category": "riser",
      "confidence": "medium",
      "rank": 55
    },
    {
      "pitcher_id": 669854,
      "name": "Ronel Blanco",
      "team": "HOU",
      "rs_pitches": 2739,
      "rs_skill": 0.0101,
      "po_pitches": 50,
      "po_skill": 0.0351,
      "skill_delta": 0.025,
      "category": "riser",
      "confidence": "low",
      "rank": 56
    },
    {
      "pitcher_id": 663947,
      "name": "Tyler Holton",
      "team": "DET",
      "rs_pitches": 1334,
      "rs_skill": 0.0088,
      "po_pitches": 107,
      "po_skill": 0.0324,
      "skill_delta": 0.0236,
      "category": "riser",
      "confidence": "medium",
      "rank": 57
    },
    {
      "pitcher_id": 640455,
      "name": "Sean Manaea",
      "team": "NYM",
      "rs_pitches": 2902,
      "rs_skill": 0.0303,
      "po_pitches": 326,
      "po_skill": 0.0089,
      "skill_delta": -0.0214,
      "category": "faller",
      "confidence": "high",
      "rank": 58
    },
    {
      "pitcher_id": 668964,
      "name": "Tobias Myers",
      "team": "MIL",
      "rs_pitches": 2145,
      "rs_skill": -0.0329,
      "po_pitches": 65,
      "po_skill": -0.0142,
      "skill_delta": 0.0187,
      "category": "neutral",
      "confidence": "low",
      "rank": 59
    },
    {
      "pitcher_id": 681857,
      "name": "Reese Olson",
      "team": "DET",
      "rs_pitches": 1848,
      "rs_skill": -0.0134,
      "po_pitches": 146,
      "po_skill": 0.005,
      "skill_delta": 0.0184,
      "category": "neutral",
      "confidence": "medium",
      "rank": 60
    },
    {
      "pitcher_id": 676440,
      "name": "Tanner Bibee",
      "team": "CLE",
      "rs_pitches": 2842,
      "rs_skill": 0.0193,
      "po_pitches": 249,
      "po_skill": 0.0366,
      "skill_delta": 0.0173,
      "category": "neutral",
      "confidence": "high",
      "rank": 61
    },
    {
      "pitcher_id": 607625,
      "name": "Seth Lugo",
      "team": "KC",
      "rs_pitches": 3102,
      "rs_skill": -0.007,
      "po_pitches": 168,
      "po_skill": -0.0237,
      "skill_delta": -0.0167,
      "category": "neutral",
      "confidence": "medium",
      "rank": 62
    },
    {
      "pitcher_id": 500779,
      "name": "Jose Quintana",
      "team": "NYM",
      "rs_pitches": 2738,
      "rs_skill": -0.0203,
      "po_pitches": 266,
      "po_skill": -0.0359,
      "skill_delta": -0.0156,
      "category": "neutral",
      "confidence": "high",
      "rank": 63
    },
    {
      "pitcher_id": 641703,
      "name": "Brent Honeywell",
      "team": "LAD",
      "rs_pitches": 593,
      "rs_skill": -0.0524,
      "po_pitches": 170,
      "po_skill": -0.0385,
      "skill_delta": 0.0139,
      "category": "neutral",
      "confidence": "medium",
      "rank": 64
    },
    {
      "pitcher_id": 608379,
      "name": "Michael Wacha",
      "team": "KC",
      "rs_pitches": 2595,
      "rs_skill": -0.006,
      "po_pitches": 134,
      "po_skill": -0.0197,
      "skill_delta": -0.0137,
      "category": "neutral",
      "confidence": "medium",
      "rank": 65
    },
    {
      "pitcher_id": 664849,
      "name": "Danny Young",
      "team": "NYM",
      "rs_pitches": 667,
      "rs_skill": 0.0349,
      "po_pitches": 67,
      "po_skill": 0.0477,
      "skill_delta": 0.0128,
      "category": "neutral",
      "confidence": "low",
      "rank": 66
    },
    {
      "pitcher_id": 592094,
      "name": "Jason Adam",
      "team": "SD",
      "rs_pitches": 1081,
      "rs_skill": 0.0767,
      "po_pitches": 83,
      "po_skill": 0.0861,
      "skill_delta": 0.0094,
      "category": "neutral",
      "confidence": "low",
      "rank": 67
    },
    {
      "pitcher_id": 592773,
      "name": "Ryne Stanek",
      "team": "NYM",
      "rs_pitches": 974,
      "rs_skill": 0.0193,
      "po_pitches": 138,
      "po_skill": 0.0122,
      "skill_delta": -0.0071,
      "category": "neutral",
      "confidence": "medium",
      "rank": 68
    },
    {
      "pitcher_id": 656302,
      "name": "Dylan Cease",
      "team": "SD",
      "rs_pitches": 3182,
      "rs_skill": 0.0081,
      "po_pitches": 120,
      "po_skill": 0.0021,
      "skill_delta": -0.006,
      "category": "neutral",
      "confidence": "medium",
      "rank": 69
    },
    {
      "pitcher_id": 657612,
      "name": "Tim Hill",
      "team": "NYY",
      "rs_pitches": 952,
      "rs_skill": -0.0207,
      "po_pitches": 124,
      "po_skill": -0.0264,
      "skill_delta": -0.0057,
      "category": "neutral",
      "confidence": "medium",
      "rank": 70
    },
    {
      "pitcher_id": 682120,
      "name": "Tim Herrin",
      "team": "CLE",
      "rs_pitches": 1006,
      "rs_skill": -0.0111,
      "po_pitches": 121,
      "po_skill": -0.0062,
      "skill_delta": 0.0049,
      "category": "neutral",
      "confidence": "medium",
      "rank": 71
    },
    {
      "pitcher_id": 669373,
      "name": "Tarik Skubal",
      "team": "DET",
      "rs_pitches": 2796,
      "rs_skill": 0.0368,
      "po_pitches": 262,
      "po_skill": 0.034,
      "skill_delta": -0.0028,
      "category": "neutral",
      "confidence": "high",
      "rank": 72
    },
    {
      "pitcher_id": 643410,
      "name": "Mark Leiter Jr.",
      "team": "NYY",
      "rs_pitches": 1011,
      "rs_skill": 0.0647,
      "po_pitches": 88,
      "po_skill": 0.066,
      "skill_delta": 0.0013,
      "category": "neutral",
      "confidence": "low",
      "rank": 73
    },
    {
      "pitcher_id": 663773,
      "name": "Bryan Hoeing",
      "team": "SD",
      "rs_pitches": 781,
      "rs_skill": -0.0066,
      "po_pitches": 57,
      "po_skill": -0.0077,
      "skill_delta": -0.0011,
      "category": "neutral",
      "confidence": "low",
      "rank": 74
    },
    {
      "pitcher_id": 607074,
      "name": "Carlos Rod\u00f3n",
      "team": "NYY",
      "rs_pitches": 3092,
      "rs_skill": 0.0042,
      "po_pitches": 313,
      "po_skill": 0.0034,
      "skill_delta": -0.0008,
      "category": "neutral",
      "confidence": "high",
      "rank": 75
    },
    {
      "pitcher_id": 621242,
      "name": "Edwin D\u00edaz",
      "team": "NYM",
      "rs_pitches": 909,
      "rs_skill": 0.0445,
      "po_pitches": 161,
      "po_skill": 0.0447,
      "skill_delta": 0.0002,
      "category": "neutral",
      "confidence": "medium",
      "rank": 76
    },
    {
      "pitcher_id": 664285,
      "name": "Framber Valdez",
      "team": "HOU",
      "rs_pitches": 2489,
      "rs_skill": -0.0105,
      "po_pitches": 78,
      "po_skill": -0.0105,
      "skill_delta": 0.0,
      "category": "neutral",
      "confidence": "low",
      "rank": 77
    }
  ]
}